LICENSE
MANIFEST.in
README
setup.cfg
setup.py
examples/basic.py
examples/basic_client.py
examples/default.yaml
turtl/__init__.py
turtl/config.py
turtl/engine.py
turtl/proxy.py
turtl/service.py
turtl.egg-info/PKG-INFO
turtl.egg-info/SOURCES.txt
turtl.egg-info/dependency_links.txt
turtl.egg-info/not-zip-safe
turtl.egg-info/requires.txt
turtl.egg-info/top_level.txt
turtl/test/__init__.py
turtl/test/test_engine.py
turtl/test/test_proxy.py
twisted/plugins/turtl_plugin.py