Metadata-Version: 1.0
Name: turtl
Version: 0.0.4
Summary: Turtl is an HTTP proxy whose purpose is to throttle connections to
